trafilatura/__init__.py
trafilatura/baseline.py
trafilatura/cli.py
trafilatura/cli_utils.py
trafilatura/core.py
trafilatura/deduplication.py
trafilatura/downloads.py
trafilatura/external.py
trafilatura/feeds.py
trafilatura/gui.py
trafilatura/htmlprocessing.py
trafilatura/json_metadata.py
trafilatura/main_extractor.py
trafilatura/meta.py
trafilatura/metadata.py
trafilatura/readability_lxml.py
trafilatura/settings.cfg
trafilatura/settings.py
trafilatura/sitemaps.py
trafilatura/spider.py
trafilatura/utils.py
trafilatura/xml.py
trafilatura/xpaths.py
trafilatura/data/tei_corpus.dtd
trafilatura-1.12.2.dist-info/LICENSE
trafilatura-1.12.2.dist-info/METADATA
trafilatura-1.12.2.dist-info/WHEEL
trafilatura-1.12.2.dist-info/entry_points.txt
trafilatura-1.12.2.dist-info/top_level.txt
trafilatura-1.12.2.dist-info/RECORD
